iotery_python_server_sdk/Iotery.py
iotery_python_server_sdk/README.md
iotery_python_server_sdk/__init__.py
iotery_python_server_sdk/api.json
iotery_python_server_sdk-0.1.6.data/data/api/api.json
iotery_python_server_sdk-0.1.6.dist-info/METADATA
iotery_python_server_sdk-0.1.6.dist-info/WHEEL
iotery_python_server_sdk-0.1.6.dist-info/top_level.txt
iotery_python_server_sdk-0.1.6.dist-info/RECORD
