Metadata-Version: 2.1
Name: iotery-python-server-sdk
Version: 0.1.6
Summary: iotery.io python server SDK
Home-page: https://github.com/bjyurkovich/iotery-python-server-sdk
Author: bjyurkovich
Author-email: bj.yurkovich@technicity.io
License: MIT
Platform: UNKNOWN
Classifier: Programming Language :: Python :: 3
Classifier: License :: OSI Approved :: MIT License
Classifier: Operating System :: OS Independent
Requires-Dist: requests
